llm_tr/__init__.py
llm_tr-0.2.1.dist-info/WHEEL
llm_tr-0.2.1.dist-info/entry_points.txt
llm_tr-0.2.1.dist-info/METADATA
llm_tr-0.2.1.dist-info/RECORD
