Metadata-Version: 2.3
Name: llm-tr
Version: 0.2.1
Summary: Use LLM to translate in your shell
Author: Martín Gaitán
License: Apache-2.0
Classifier: License :: OSI Approved :: Apache Software License
Requires-Dist: llm
Requires-Dist: pytest ; extra == 'test'
Requires-Python: >=3.10
Project-URL: CI, https://github.com/mgaitan/llm-tr/actions/workflows/ci.yml
Project-URL: Changelog, https://github.com/mgaitan/llm-tr/releases
Project-URL: Homepage, https://github.com/mgaitan/llm-tr
Project-URL: Issues, https://github.com/mgaitan/llm-tr/issues
Provides-Extra: test
